hyptorch/__init__.py
hyptorch/_config.py
hyptorch/exceptions.py
hyptorch/py.typed
hyptorch/utils.py
hyptorch/manifolds/__init__.py
hyptorch/manifolds/base.py
hyptorch/manifolds/klein_disk.py
hyptorch/manifolds/poincare_ball.py
hyptorch/nn/__init__.py
hyptorch/nn/_base.py
hyptorch/nn/_mixins.py
hyptorch/nn/functional.py
hyptorch/nn/modules/linear.py
hyptorch/nn/modules/manifold.py
hyptorch/nn/modules/mean.py
hyptorch/nn/modules/mlr.py
hyptorch/tensor/__init__.py
hyptorch/tensor/autograd.py
hyptorch/tensor/ops.py
hyptorch/transforms/__init__.py
hyptorch/transforms/base.py
hyptorch/transforms/poincare_klein.py
hyptorch-1.3.1.dist-info/licenses/LICENSE
hyptorch-1.3.1.dist-info/METADATA
hyptorch-1.3.1.dist-info/WHEEL
hyptorch-1.3.1.dist-info/top_level.txt
hyptorch-1.3.1.dist-info/RECORD
